WATER_SORT_PUZZLE/water_sort_puzzle.py
WATER_SORT_PUZZLE-1.dist-info/LICENSE
WATER_SORT_PUZZLE-1.dist-info/METADATA
WATER_SORT_PUZZLE-1.dist-info/WHEEL
WATER_SORT_PUZZLE-1.dist-info/entry_points.txt
WATER_SORT_PUZZLE-1.dist-info/top_level.txt
WATER_SORT_PUZZLE-1.dist-info/RECORD
