Metadata-Version: 2.1
Name: WATER-SORT-PUZZLE
Version: 1
Summary: This package contains implementation of the game "WATER_SORT_PUZZLE" on command line interface.
Home-page: https://github.com/GlobalCreativeCommunityFounder/WATER_SORT_PUZZLE
Author: GlobalCreativeCommunityFounder
Author-email: globalcreativecommunityfounder@gmail.com
License: MIT
Platform: UNKNOWN
Classifier: Programming Language :: Python :: 3
Classifier: Programming Language :: Python :: 3.7
